is_not_odd.py
isnotodd-0.1.26.dist-info/METADATA
isnotodd-0.1.26.dist-info/WHEEL
isnotodd-0.1.26.dist-info/top_level.txt
isnotodd-0.1.26.dist-info/RECORD
