Metadata-Version: 2.4
Name: isnotodd
Version: 0.1.26
Summary: use this library if you want to check if an integer is even or not and you think '%' is stupid.
Requires-Python: >=3.13
